README
setup.py
gyuto/__init__.py
gyuto/cli.py
gyuto.egg-info/PKG-INFO
gyuto.egg-info/SOURCES.txt
gyuto.egg-info/dependency_links.txt
gyuto.egg-info/entry_points.txt
gyuto.egg-info/requires.txt
gyuto.egg-info/top_level.txt
gyuto/commands/__init__.py
gyuto/commands/gyuto_chart.py
gyuto/commands/gyuto_diff.py
gyuto/commands/gyuto_hosts.py
gyuto/commands/gyuto_lookup.py
gyuto/commands/gyuto_merge.py
gyuto/commands/gyuto_search.py
gyuto/commands/gyuto_show.py
gyuto/commands/gyuto_stats.py
gyuto/core/__init__.py
gyuto/core/diff.py
gyuto/core/models.py
gyuto/core/resources.py
gyuto/core/results.py
gyuto/core/templates.py
gyuto/parsers/__init__.py
gyuto/parsers/nessus.py
gyuto/parsers/nexpose.py
gyuto/parsers/nmap.py
gyuto/parsers/qualys.py