Metadata-Version: 1.0
Name: gyuto
Version: 0.1.2
Summary: A tool to slice and dice vulnerability scan data
Home-page: http://bitbucket.org/skew/gyuto
Author: John Askew
Author-email: john.askew@gmail.com
License: GNU General Public License v3 (GPLv3)
Platform: UNKNOWN
